[
  {
    "id": 1,
    "nama": "Nailla Rahma",
    "jabatan": "Ketua Kelas",
    "fotoUrl": "/assets/images/naila1.jpeg"
  },
  {
    "id": 2,
    "nama": "Zulfaa Kamiliyya",
    "jabatan": "Wakil Ketua",
    "fotoUrl": "/assets/images/julpa.jpeg"
  },
  {
    "id": 3,
    "nama": "Ditan Aulia M",
    "jabatan": "Sekretaris 1",
    "fotoUrl": "/assets/images/ditan.jpeg"
  },
  {
    "id": 4,
    "nama": "Retno W",
    "jabatan": "Bendahara 1",
    "fotoUrl": "/assets/images/retnoo.jpeg"
  },
  {
    "id": 5,
    "nama": "Stevanny Cecilia",
    "jabatan": "Bendahara 2",
    "fotoUrl": "/assets/images/vanny.jpeg"
  },
  {
    "id": 6,
    "nama": "Aqeylla Balqis",
    "jabatan": "Sekretaris 2",
    "fotoUrl": "/assets/images/aqella.jpeg"
  },
  {
    "id": 7,
    "nama": "Carlo Julio",
    "jabatan": "Koordinator Olahraga",
    "fotoUrl": "/assets/images/carlo.jpeg"
  },
  {
    "id": 8,
    "nama": "Wildan Nur A",
    "jabatan": "Koordinator IT",
    "fotoUrl": "/assets/images/wildan.png"
  }
]
